nwbext_ecog/__init__.py
nwbext_ecog/ecog.py
nwbext_ecog/ecog_auto.py
nwbext_ecog/gen_ecog_yaml.py
nwbext_ecog/test_ecog_manual.py
nwbext_ecog-0.7.2.data/data/ndx_specs/ecog.extensions.yaml
nwbext_ecog-0.7.2.data/data/ndx_specs/ecog.namespace.yaml
nwbext_ecog-0.7.2.dist-info/LICENSE
nwbext_ecog-0.7.2.dist-info/METADATA
nwbext_ecog-0.7.2.dist-info/WHEEL
nwbext_ecog-0.7.2.dist-info/top_level.txt
nwbext_ecog-0.7.2.dist-info/RECORD
