Metadata-Version: 2.1
Name: nwbext-ecog
Version: 0.7.2
Summary: Convert data to nwb
Home-page: UNKNOWN
Author: Ben Dichter
Author-email: ben.dichter@gmail.com
License: UNKNOWN
Keywords: nwb,extension
Platform: UNKNOWN
Requires-Dist: pynwb
